sentipy/__init__.py
sentipy/_typing_imports.py
sentipy/py.typed
sentipy/sentipy.py
sentipy/tests/.gitignore
sentipy/tests/sentipy_tests.py
sentipy/ws.py
sentiment_investor-2.1.0.dist-info/LICENSE
sentiment_investor-2.1.0.dist-info/WHEEL
sentiment_investor-2.1.0.dist-info/METADATA
sentiment_investor-2.1.0.dist-info/RECORD
