Metadata-Version: 2.1
Name: sentiment-investor
Version: 2.1.0
Summary: Access the Sentiment Investor API through Python
Home-page: https://sentimentinvestor.com/
License: MIT
Author: Robert Stok
Author-email: rs.stok@gmail.com
Requires-Python: >=3.8,<4.0
Classifier: License :: OSI Approved :: MIT License
Classifier: Natural Language :: English
Classifier: Operating System :: OS Independent
Classifier: Programming Language :: Python :: 3
Classifier: Programming Language :: Python :: 3.8
Classifier: Programming Language :: Python :: 3.9
Classifier: Typing :: Typed
Requires-Dist: beartype (>=0.7.1,<0.8.0)
Requires-Dist: requests (>=2.26.0,<3.0.0)
Requires-Dist: websocket-client (>=1.1.0,<2.0.0)
Project-URL: Bug Tracker, https://github.com/sentimentinvestor/sentipy/issues
Project-URL: Documentation, https://docs.sentimentinvestor.com/python/
Project-URL: Repository, https://github.com/sentimentinvestor/sentipy
